edanif/__init__.py
edanif/eda_nif.py
edanif/vis_nif.py
edanif/process/__init__.py
edanif/process/preprocess.py
edanif/process/registration.py
edanif/process/resampling.py
edanif/process/trans_morph.py
edanif/utils/__init__.py
edanif/utils/util.py
edanif-0.1.7.dist-info/LICENSE
edanif-0.1.7.dist-info/METADATA
edanif-0.1.7.dist-info/WHEEL
edanif-0.1.7.dist-info/top_level.txt
edanif-0.1.7.dist-info/RECORD
