Metadata-Version: 2.1
Name: edanif
Version: 0.1.7
Summary: EDA-NIf creates a dataframe containing meta information of NIfTi files and provides several useful features.
Home-page: https://github.com/DSDanielPark/EDA-NIf
Author: parkminwoo
Author-email: parkminwoo1991@gmail.com
Requires-Python: >=3.6
License-File: LICENSE
Requires-Dist: nibabel
Requires-Dist: pandas
Requires-Dist: numpy
Requires-Dist: matplotlib
Requires-Dist: tqdm
Requires-Dist: SimpleITK
Requires-Dist: monai
Requires-Dist: scikit-image
Requires-Dist: ipykernel
